{
  "uid" : "6dc3d5cd98254c97",
  "name" : "TestPersonal.test_personal_01",
  "title" : "Test personal 01",
  "time" : {
    "start" : 1534924927520,
    "stop" : 1534924927521,
    "duration" : 1
  },
  "summary" : {
    "attachments" : 0,
    "steps" : 0
  },
  "failure" : {
    "message" : "Skipped: Not suitable with selected labels: ('feature', 'Home').",
    "stackTrace" : ""
  },
  "description" : {
    "value" : "\n            用例描述：未登陆状态下更新Personal个人简介\n        ",
    "type" : "TEXT"
  },
  "severity" : "BLOCKER",
  "status" : "CANCELED",
  "testId" : null,
  "suite" : {
    "uid" : "45e7bd017bd4c663",
    "name" : "test_personal",
    "title" : "Test personal"
  },
  "steps" : [ ],
  "attachments" : [ ],
  "issues" : [ ],
  "labels" : [ {
    "name" : "suite-name",
    "value" : "test_personal"
  }, {
    "name" : "thread",
    "value" : "68122-MainThread"
  }, {
    "name" : "story",
    "value" : "Personal"
  }, {
    "name" : "severity",
    "value" : "blocker"
  }, {
    "name" : "framework",
    "value" : "pytest"
  }, {
    "name" : "suite-title",
    "value" : null
  }, {
    "name" : "host",
    "value" : "xiaoxideMacBook-Pro.local"
  }, {
    "name" : "language",
    "value" : "cpython3"
  } ],
  "parameters" : [ ]
}