{
  "uid" : "b81fb3e532ac4977",
  "name" : "TestBasic.test_basic_02",
  "title" : "Test basic 02",
  "time" : {
    "start" : 1534921761211,
    "stop" : 1534921761615,
    "duration" : 404
  },
  "summary" : {
    "attachments" : 2,
    "steps" : 0
  },
  "failure" : null,
  "description" : {
    "value" : "\n            用例描述：登陆状态下查看基础设置\n        ",
    "type" : "TEXT"
  },
  "severity" : "BLOCKER",
  "status" : "PASSED",
  "testId" : null,
  "suite" : {
    "uid" : "85f12e8414d714d5",
    "name" : "test_basic",
    "title" : "Test basic"
  },
  "steps" : [ ],
  "attachments" : [ {
    "title" : "Captured log call",
    "source" : "e6bc15fe-c31d-478c-8916-9599cf891e1c-attachment.txt",
    "type" : "text/plain",
    "size" : 708,
    "uid" : "28dad66f8bcab79a"
  }, {
    "title" : "Captured log setup",
    "source" : "f50060aa-a798-4cd0-9efc-af3653277b21-attachment.txt",
    "type" : "text/plain",
    "size" : 151,
    "uid" : "b1f4d271d3762d30"
  } ],
  "issues" : [ ],
  "labels" : [ {
    "name" : "story",
    "value" : "Basic"
  }, {
    "name" : "suite-name",
    "value" : "test_basic"
  }, {
    "name" : "severity",
    "value" : "blocker"
  }, {
    "name" : "feature",
    "value" : "Home"
  }, {
    "name" : "framework",
    "value" : "pytest"
  }, {
    "name" : "suite-title",
    "value" : null
  }, {
    "name" : "host",
    "value" : "xiaoxideMacBook-Pro.local"
  }, {
    "name" : "thread",
    "value" : "62502-MainThread"
  }, {
    "name" : "language",
    "value" : "cpython3"
  } ],
  "parameters" : [ ]
}