{
  "hash" : "9ae4a52f46fbba0c959575303f697deb73e72d63",
  "data" : [ {
    "statistic" : {
      "total" : 2,
      "passed" : 0,
      "pending" : 0,
      "canceled" : 0,
      "failed" : 0,
      "broken" : 2
    },
    "time" : {
      "start" : 1559550801138,
      "stop" : 1559550801138,
      "duration" : 0
    },
    "name" : "total",
    "type" : "TOTAL"
  }, {
    "name" : "defects",
    "type" : "DEFECTS",
    "data" : [ {
      "count" : 2,
      "message" : "failed",
      "status" : "BROKEN"
    } ]
  }, {
    "name" : "xunit",
    "type" : "TITLE_STATISTICS",
    "data" : [ {
      "title" : "Collection phase",
      "statistic" : {
        "total" : 2,
        "passed" : 0,
        "pending" : 0,
        "canceled" : 0,
        "failed" : 0,
        "broken" : 2
      }
    } ]
  }, {
    "name" : "behaviors",
    "type" : "TITLE_STATISTICS",
    "data" : [ {
      "title" : "Without feature",
      "statistic" : {
        "total" : 2,
        "passed" : 0,
        "pending" : 0,
        "canceled" : 0,
        "failed" : 0,
        "broken" : 2
      }
    } ]
  }, {
    "name" : "environment",
    "type" : "KEY_VALUE",
    "data" : [ ]
  } ]
}